[
    {
        "key": "dbln",
        "value": "%7B%2261581279514397%22%3A%22Wa5bTur5%22%7D",
        "domain": "facebook.com",
        "path": "/login/device-based/",
        "hostOnly": false,
        "creation": "2025-09-26T13:24:06.664Z",
        "lastAccessed": "2025-09-26T13:24:06.665Z"
    },
    {
        "key": "datr",
        "value": "mIjUaG8W9mEvcNlm8Uij5guX",
        "domain": "facebook.com",
        "path": "/",
        "hostOnly": false,
        "creation": "2025-09-26T13:24:06.665Z",
        "lastAccessed": "2025-09-26T13:24:06.665Z"
    },
    {
        "key": "sb",
        "value": "mIjUaHoXNbnP8TqX83Jz1pL9",
        "domain": "facebook.com",
        "path": "/",
        "hostOnly": false,
        "creation": "2025-09-26T13:24:06.665Z",
        "lastAccessed": "2025-09-26T13:24:06.665Z"
    },
    {
        "key": "locale",
        "value": "en_US",
        "domain": "facebook.com",
        "path": "/",
        "hostOnly": false,
        "creation": "2025-09-26T13:24:06.665Z",
        "lastAccessed": "2025-09-26T13:24:06.665Z"
    },
    {
        "key": "vpd",
        "value": "v1%3B1024x509x2.125",
        "domain": "facebook.com",
        "path": "/",
        "hostOnly": false,
        "creation": "2025-09-26T13:24:06.665Z",
        "lastAccessed": "2025-09-26T13:24:06.665Z"
    },
    {
        "key": "dpr",
        "value": "2.125",
        "domain": "facebook.com",
        "path": "/",
        "hostOnly": false,
        "creation": "2025-09-26T13:24:06.665Z",
        "lastAccessed": "2025-09-26T13:24:06.665Z"
    },
    {
        "key": "pas",
        "value": "61581279514397%3AQF0cL8kVWF",
        "domain": "facebook.com",
        "path": "/",
        "hostOnly": false,
        "creation": "2025-09-26T13:24:06.665Z",
        "lastAccessed": "2025-09-26T13:24:06.665Z"
    },
    {
        "key": "ps_l",
        "value": "1",
        "domain": "facebook.com",
        "path": "/",
        "hostOnly": false,
        "creation": "2025-09-26T13:24:06.665Z",
        "lastAccessed": "2025-09-26T13:24:06.665Z"
    },
    {
        "key": "ps_n",
        "value": "1",
        "domain": "facebook.com",
        "path": "/",
        "hostOnly": false,
        "creation": "2025-09-26T13:24:06.665Z",
        "lastAccessed": "2025-09-26T13:24:06.665Z"
    },
    {
        "key": "oo",
        "value": "v1",
        "domain": "facebook.com",
        "path": "/",
        "hostOnly": false,
        "creation": "2025-09-26T13:24:06.665Z",
        "lastAccessed": "2025-09-26T13:24:06.665Z"
    },
    {
        "key": "c_user",
        "value": "61581279514397",
        "domain": "facebook.com",
        "path": "/",
        "hostOnly": false,
        "creation": "2025-09-26T13:24:06.665Z",
        "lastAccessed": "2025-09-26T13:24:06.665Z"
    },
    {
        "key": "xs",
        "value": "18%3AtFwpkMM1_ezoDw%3A2%3A1758881380%3A-1%3A-1",
        "domain": "facebook.com",
        "path": "/",
        "hostOnly": false,
        "creation": "2025-09-26T13:24:06.665Z",
        "lastAccessed": "2025-09-26T13:24:06.665Z"
    },
    {
        "key": "fr",
        "value": "09Ro3xpCUPF3TdCQo.AWfwph7scyo-5thLG1489o6bDKbOBLve1h8-6BXOjMVmE-8qb1w.Bo1goL..AAA.0.0.Bo1pPj.AWehCtUOkLG0u1DkU7mN02mRyP4",
        "domain": "facebook.com",
        "path": "/",
        "hostOnly": false,
        "creation": "2025-09-26T13:24:06.665Z",
        "lastAccessed": "2025-09-26T13:24:06.665Z"
    },
    {
        "key": "fbl_st",
        "value": "101737679%3BT%3A29314883",
        "domain": "facebook.com",
        "path": "/",
        "hostOnly": false,
        "creation": "2025-09-26T13:24:06.665Z",
        "lastAccessed": "2025-09-26T13:24:06.665Z"
    },
    {
        "key": "wl_cbv",
        "value": "v2%3Bclient_version%3A2935%3Btimestamp%3A1758893027",
        "domain": "facebook.com",
        "path": "/",
        "hostOnly": false,
        "creation": "2025-09-26T13:24:06.665Z",
        "lastAccessed": "2025-09-26T13:24:06.665Z"
    }
]
